{
    "id": "210",
    "url": "https://yts.ag/movie/altman-2014",
    "imdb_code": "tt2404171",
    "title": "Altman",
    "title_long": "Altman (2014)",
    "slug": "altman-2014",
    "year": "2014",
    "rating": "6.80",
    "runtime": "96",
    "genres": [
        "Documentary"
    ],
    "language": "English",
    "mpa_rating": "15",
    "background_image": "altman-2014-background.jpg",
    "small_cover_image": "altman-2014-small-cover.jpg",
    "medium_cover_image": "altman-2014-medium-cover.jpg",
    "state": "ok",
    "date_uploaded": "2015-10-31 21:20:57",
    "date_uploaded_unix": 1446340857
}
