{
    "id": "151",
    "url": "https://yts.ag/movie/perfect-mothers-2013",
    "imdb_code": "tt2103267",
    "title": "Perfect Mothers",
    "title_long": "Perfect Mothers (2013)",
    "slug": "perfect-mothers-2013",
    "year": "2013",
    "rating": "6.20",
    "runtime": "0",
    "genres": [
        "Drama",
        "Romance"
    ],
    "language": "English",
    "mpa_rating": "R",
    "background_image": "perfect-mothers-2013-background.jpg",
    "small_cover_image": "perfect-mothers-2013-small-cover.jpg",
    "medium_cover_image": "perfect-mothers-2013-medium-cover.jpg",
    "state": "ok",
    "date_uploaded": "2015-10-31 21:10:05",
    "date_uploaded_unix": 1446340205
}
